mapwidgets/__init__.py
mapwidgets/admin.py
mapwidgets/constants.py
mapwidgets/settings.py
mapwidgets/utils.py
mapwidgets/widgets.py
mapwidgets/locale/de/LC_MESSAGES/django.mo
mapwidgets/locale/de/LC_MESSAGES/django.po
mapwidgets/locale/en/LC_MESSAGES/django.mo
mapwidgets/locale/en/LC_MESSAGES/django.po
mapwidgets/locale/es/LC_MESSAGES/django.mo
mapwidgets/locale/es/LC_MESSAGES/django.po
mapwidgets/locale/et/LC_MESSAGES/django.mo
mapwidgets/locale/et/LC_MESSAGES/django.po
mapwidgets/locale/it/LC_MESSAGES/django.mo
mapwidgets/locale/it/LC_MESSAGES/django.po
mapwidgets/locale/ja/LC_MESSAGES/django.mo
mapwidgets/locale/ja/LC_MESSAGES/django.po
mapwidgets/locale/pl/LC_MESSAGES/django.mo
mapwidgets/locale/pl/LC_MESSAGES/django.po
mapwidgets/locale/pt_BR/LC_MESSAGES/django.mo
mapwidgets/locale/pt_BR/LC_MESSAGES/django.po
mapwidgets/locale/ru/LC_MESSAGES/django.mo
mapwidgets/locale/ru/LC_MESSAGES/django.po
mapwidgets/locale/sk/LC_MESSAGES/django.mo
mapwidgets/locale/sk/LC_MESSAGES/django.po
mapwidgets/locale/zh/.DS_Store
mapwidgets/locale/zh/LC_MESSAGES/django.mo
mapwidgets/locale/zh/LC_MESSAGES/django.po
mapwidgets/static/mapwidgets/.DS_Store
mapwidgets/static/mapwidgets/css/magnific-popup.css
mapwidgets/static/mapwidgets/css/magnific-popup.min.css
mapwidgets/static/mapwidgets/css/map_widgets.css
mapwidgets/static/mapwidgets/css/map_widgets.min.css
mapwidgets/static/mapwidgets/font/fontello.eot
mapwidgets/static/mapwidgets/font/fontello.svg
mapwidgets/static/mapwidgets/font/fontello.ttf
mapwidgets/static/mapwidgets/font/fontello.woff
mapwidgets/static/mapwidgets/font/fontello.woff2
mapwidgets/static/mapwidgets/images/no-map-image.png
mapwidgets/static/mapwidgets/images/ripple.gif
mapwidgets/static/mapwidgets/js/django_mw_base.js
mapwidgets/static/mapwidgets/js/jquery.custom.magnific-popup.js
mapwidgets/static/mapwidgets/js/jquery.custom.magnific-popup.min.js
mapwidgets/static/mapwidgets/js/jquery_class.js
mapwidgets/static/mapwidgets/js/jquery_init.js
django_map_widgets-0.5.0.dist-info/LICENSE
django_map_widgets-0.5.0.dist-info/METADATA
django_map_widgets-0.5.0.dist-info/WHEEL
django_map_widgets-0.5.0.dist-info/top_level.txt
django_map_widgets-0.5.0.dist-info/RECORD
