Metadata-Version: 2.1
Name: django-map-widgets
Version: 0.5.0
Summary: Configurable and user-friendly map widgets for GeoDjango fields
Home-page: https://github.com/erdem/django-map-widgets
Author: Erdem Ozkol
Author-email: mapwidgets@erdemozkol.com
License: MIT
Project-URL: Documentation, https://django-map-widgets.readthedocs.io/
Project-URL: Source, https://github.com/erdem/django-map-widgets
Project-URL: Demo Project, https://github.com/erdem/django-map-widgets/tree/main/demo
Keywords: django map-widgets geodjango geolocation mapbox google map leaflet interactive-maps
Classifier: Development Status :: 5 - Production/Stable
Classifier: Environment :: Web Environment
Classifier: Framework :: Django
Classifier: Intended Audience :: Developers
Classifier: License :: OSI Approved :: MIT License
Classifier: Operating System :: OS Independent
Classifier: Programming Language :: Python
Classifier: Topic :: Software Development :: Libraries :: Python Modules
License-File: LICENSE
